{
  "file_name": "05 bw.jpg",
  "file_size": 3440955,
  "sha256": "44729a53564b954d4c37a87360e00fd039bf4e1aa31c2a8d81db253d8e94a2ff",
  "phash": "b8e1a7125be6a315",
  "metadata": {
    "ImageWidth": "2156",
    "ImageLength": "3234",
    "BitsPerSample": "(8, 8, 8)",
    "PhotometricInterpretation": "2",
    "ResolutionUnit": "2",
    "ExifOffset": "312",
    "Make": "Canon",
    "Model": "Canon EOS-1D X",
    "Software": "Adobe Photoshop CC 2019 (Windows)",
    "Orientation": "1",
    "DateTime": "2018:11:20 15:15:44",
    "YResolution": "300.0",
    "SamplesPerPixel": "3",
    "XResolution": "300.0",
    "Artist": "Christina Lundeen",
    "ExifVersion": "b'0230'",
    "ShutterSpeedValue": "7.643856",
    "ApertureValue": "6.0",
    "DateTimeOriginal": "2018:09:20 13:59:14",
    "DateTimeDigitized": "2018:09:20 13:59:14",
    "ExposureBiasValue": "0.0",
    "MaxApertureValue": "0.625",
    "MeteringMode": "5",
    "ColorSpace": "65535",
    "Flash": "9",
    "FocalLength": "50.0",
    "ExifImageWidth": "2156",
    "ExifImageHeight": "3234",
    "SceneCaptureType": "0",
    "FocalPlaneXResolution": "1440.0",
    "FocalPlaneYResolution": "1440.0",
    "SubsecTime": "27",
    "SubsecTimeOriginal": "27",
    "SubsecTimeDigitized": "27",
    "FocalPlaneResolutionUnit": "3",
    "ExposureTime": "0.005",
    "FNumber": "8.0",
    "ExposureProgram": "1",
    "CustomRendered": "0",
    "ISOSpeedRatings": "320",
    "ExposureMode": "1",
    "SensitivityType": "2",
    "WhiteBalance": "1",
    "RecommendedExposureIndex": "320",
    "BodySerialNumber": "352012000078",
    "LensSpecification": "(50.0, 50.0, nan, nan)",
    "LensModel": "EF50mm f/1.2L USM",
    "LensSerialNumber": "000040b2b8"
  },
  "c2pa": {
    "present": false,
    "details": "C2PA detection not yet implemented."
  },
  "analysis_date": "2026-03-19T12:48:03.555097"
}